typeddict2jsonschema/__init__.py
typeddict2jsonschema/__main__.py
typeddict2jsonschema/cli.py
typeddict2jsonschema/jsonschemagenerator.py
typeddict2jsonschema/utils.py
typeddict2jsonschema-0.0.1.dist-info/METADATA
typeddict2jsonschema-0.0.1.dist-info/WHEEL
typeddict2jsonschema-0.0.1.dist-info/entry_points.txt
typeddict2jsonschema-0.0.1.dist-info/top_level.txt
typeddict2jsonschema-0.0.1.dist-info/RECORD
