Metadata-Version: 2.1
Name: typeddict2jsonschema
Version: 0.0.1
Summary: UNKNOWN
Author: Mirko Bez
Author-email: bez.mirko@gmail.com
License: UNKNOWN
Platform: UNKNOWN
Requires-Dist: jsonschema
